[
  {
    "source": "Bleeping Computer",
    "title": "Chinese state hackers target telcos with new malware toolkit",
    "link": "https://www.bleepingcomputer.com/news/security/chinese-state-hackers-target-telcos-with-new-malware-toolkit/",
    "published": "2026-03-05 23:19:49"
  },
  {
    "source": "Bleeping Computer",
    "title": "Bing AI promoted fake OpenClaw GitHub repo pushing info-stealing malware",
    "link": "https://www.bleepingcomputer.com/news/security/bing-ai-promoted-fake-openclaw-github-repo-pushing-info-stealing-malware/",
    "published": "2026-03-05 22:37:34"
  },
  {
    "source": "Bleeping Computer",
    "title": "Wikipedia hit by self-propagating JavaScript worm that vandalized pages",
    "link": "https://www.bleepingcomputer.com/news/security/wikipedia-hit-by-self-propagating-javascript-worm-that-vandalized-pages/",
    "published": "2026-03-05 20:42:25"
  },
  {
    "source": "Bleeping Computer",
    "title": "WordPress membership plugin bug exploited to create admin accounts",
    "link": "https://www.bleepingcomputer.com/news/security/wordpress-membership-plugin-bug-exploited-to-create-admin-accounts/",
    "published": "2026-03-05 18:44:58"
  },
  {
    "source": "Bleeping Computer",
    "title": "FBI arrests suspect linked to $46M crypto theft from US Marshals",
    "link": "https://www.bleepingcomputer.com/news/security/fbi-arrests-suspect-linked-to-46m-crypto-theft-from-us-marshals/",
    "published": "2026-03-05 18:36:18"
  }
]