[
  {
    "source": "Bleeping Computer",
    "title": "Okta SSO accounts targeted in vishing-based data theft attacks",
    "link": "https://www.bleepingcomputer.com/news/security/okta-sso-accounts-targeted-in-vishing-based-data-theft-attacks/",
    "published": "2026-01-22 21:43:43"
  },
  {
    "source": "Bleeping Computer",
    "title": "Curl ending bug bounty program after flood of AI slop reports",
    "link": "https://www.bleepingcomputer.com/news/security/curl-ending-bug-bounty-program-after-flood-of-ai-slop-reports/",
    "published": "2026-01-22 19:01:36"
  },
  {
    "source": "Bleeping Computer",
    "title": "SmarterMail auth bypass flaw now exploited to hijack admin accounts",
    "link": "https://www.bleepingcomputer.com/news/security/smartermail-auth-bypass-flaw-now-exploited-to-hijack-admin-accounts/",
    "published": "2026-01-22 18:44:21"
  },
  {
    "source": "Bleeping Computer",
    "title": "Microsoft Teams to add brand impersonation warnings to calls",
    "link": "https://www.bleepingcomputer.com/news/microsoft/microsoft-teams-to-add-brand-impersonation-warnings-to-calls/",
    "published": "2026-01-22 16:28:47"
  },
  {
    "source": "Bleeping Computer",
    "title": "INC ransomware opsec fail allowed data recovery for 12 US orgs",
    "link": "https://www.bleepingcomputer.com/news/security/inc-ransomware-opsec-fail-allowed-data-recovery-for-12-us-orgs/",
    "published": "2026-01-22 16:21:17"
  }
]