[
  {
    "source": "The Quantum Insider",
    "title": "Sygaldry Raises $139 Million to Build Quantum Computers For AI",
    "link": "https://thequantuminsider.com/2026/05/16/sygaldry-raises-139-million-to-build-quantum-computers-for-ai-2/",
    "published": "2026-05-16 12:45:33"
  },
  {
    "source": "The Quantum Insider",
    "title": "Guest Post: Why Europe\u2019s Quantum Future Depends on Talent Hubs, Not Just Tech Milestones",
    "link": "https://thequantuminsider.com/2026/05/16/guest-post-why-europes-quantum-future-depends-on-talent-hubs-not-just-tech-milestones/",
    "published": "2026-05-16 11:24:00"
  },
  {
    "source": "The Quantum Insider",
    "title": "Xanadu Reports Revenue Jump in First Quarterly Earnings Report",
    "link": "https://thequantuminsider.com/2026/05/16/xanadu-reports-revenue-jump-in-first-quarterly-earnings-report/",
    "published": "2026-05-16 08:22:09"
  },
  {
    "source": "The Quantum Insider",
    "title": "Podcast with Bob Sorensen, Chief Quantum Analyst, Hyperion Research",
    "link": "https://thequantuminsider.com/2026/05/16/podcast-with-bob-sorensen-chief-quantum-analyst-hyperion-research/",
    "published": "2026-05-16 07:00:00"
  },
  {
    "source": "The Quantum Insider",
    "title": "NSF Announces $1.5 Billion X-Labs Initiative to Pursue Generational Breakthrough Science Efforts",
    "link": "https://thequantuminsider.com/2026/05/15/nsf-announces-1-5-billion-x-labs-initiative-to-pursue-generational-breakthrough-science-efforts/",
    "published": "2026-05-15 19:27:29"
  },
  {
    "source": "ScienceDaily (Quantum Computing)",
    "title": "Scientists finally solve the 100-year mystery behind tough tires",
    "link": "https://www.sciencedaily.com/releases/2026/05/260509210648.htm",
    "published": "2026-05-13 13:35:37"
  },
  {
    "source": "ScienceDaily (Quantum Computing)",
    "title": "Quantum breakthrough could revolutionize teleportation and computing",
    "link": "https://www.sciencedaily.com/releases/2026/05/260513034640.htm",
    "published": "2026-05-13 07:55:23"
  },
  {
    "source": "ScienceDaily (Quantum Computing)",
    "title": "New quantum algorithm solves \u201cimpossible\u201d materials problem in seconds",
    "link": "https://www.sciencedaily.com/releases/2026/05/260512202355.htm",
    "published": "2026-05-13 07:33:27"
  },
  {
    "source": "ScienceDaily (Quantum Computing)",
    "title": "Scientists put a tiny lump of metal in two places at once in record-breaking quantum experiment",
    "link": "https://www.sciencedaily.com/releases/2026/05/260509210650.htm",
    "published": "2026-05-11 12:48:46"
  },
  {
    "source": "ScienceDaily (Quantum Computing)",
    "title": "Physicists discover quantum particles that break the rules of reality",
    "link": "https://www.sciencedaily.com/releases/2026/05/260508003131.htm",
    "published": "2026-05-09 13:00:44"
  }
]